faraday_spectra/__init__.py
faraday_spectra/__version__.py
faraday_spectra/generate_spectra.py
faraday_spectra-0.1.5.dist-info/LICENSE
faraday_spectra-0.1.5.dist-info/METADATA
faraday_spectra-0.1.5.dist-info/WHEEL
faraday_spectra-0.1.5.dist-info/top_level.txt
faraday_spectra-0.1.5.dist-info/RECORD
